ktrex/__init__.py
ktrex/fs.py
ktrex/main.py
ktrex/presets.py
ktrex/render.py
ktrex/state.py
ktrex/tree.py
ktrex/tui.py
ktrex/presets/ml_project.json
ktrex-0.1.69.dist-info/licenses/LICENSE
ktrex-0.1.69.dist-info/METADATA
ktrex-0.1.69.dist-info/WHEEL
ktrex-0.1.69.dist-info/entry_points.txt
ktrex-0.1.69.dist-info/top_level.txt
ktrex-0.1.69.dist-info/RECORD
