Metadata-Version: 2.4
Name: KTrex
Version: 0.1.69
Summary: Interactive terminal-based directory structure builder
Author: AK
License: MIT
Requires-Python: >=3.10
License-File: LICENSE
Dynamic: license-file
